<?xml version="1.0" encoding="UTF-8" standalone="no"?>
<Channels>
    <Version>1.0.6</Version>
    <isClearFavCh>0</isClearFavCh>
    <isClearRecentCh>0</isClearRecentCh>
    <isClearCustomCh>0</isClearCustomCh>
    <isEncrypt>1</isEncrypt>
    <relatedChannelInfoURL>http://www.bing.com</relatedChannelInfoURL>
    <avoptions>user-agent==AppleCoreMedia/1.0.0.14C109 (Macintosh; U; Intel Mac OS X 10_10_2; zh_cn)</avoptions>
    <supportWebUrl2VideoUrl>1</supportWebUrl2VideoUrl>
    <convertURLEngineConfigV>1.7.1</convertURLEngineConfigV>
    <bufferTime4Reload>10</bufferTime4Reload>
    <reloadTime>15</reloadTime>
    <nofreshTime>25</nofreshTime>
    <loadOpenAdRate_ip>1</loadOpenAdRate_ip>
    <loadOpenAdRate_ipad>1</loadOpenAdRate_ipad>
    <loadPlayerAdRate_ipad>0</loadPlayerAdRate_ipad>
    <loadPlayerAdRate_ip>0</loadPlayerAdRate_ip>
    <!--
    <loadFullDelay>0.1</loadFullDelay>
    <bannerOnhomepageTime>100</bannerOnhomepageTime>
    <loadHomeBannerAdRate_ip>1</loadHomeBannerAdRate_ip>
     -->
    <Appstate>2</Appstate>
     <isOpenLoadConfig>1</isOpenLoadConfig>

    <playerlistURL_header>JvHeyBHCt2Wu3iyL9O/UwuGlJi/VPA0lPTU2gBYGMGuvaC9DX+H3+hnTquYA6k2V7qwsT2M9UebPf+9zd62tbQ==</playerlistURL_header>
    <playerlistURL>SErmxGC8wjPr345vfHYZQyrgKuuu6T7f78Vl0X+tv/eoidvcRP5YPsNehR8Zm0bLWM4fkLd0JGx9Zvxv8egw4/2v5WikNdf2VpjL/vkALgnIBiLXwAkh/XjQpQP9xT8V</playerlistURL>
    <IPAddressInfoURL>roPQO4b4EgaM1i9IYXFEtYtToUY41gC2RkpVtKTuGTU=</IPAddressInfoURL>
    
    <Ads>
        <AdsRate Name="AdsMogo">1</AdsRate>
        <AdsRate Name="AdsMobiSage">0</AdsRate>
        <AdsRate Name="SegIndex">0</AdsRate>
        <AdsRate Name="FullAdFrequency">13</AdsRate>
        <AdsRate Name="FullAdFrequency_ip">12</AdsRate>
    </Ads> <supportFormat>3gp,asf,avi,divx,dv,dat,flv,gxf,m2p,m2ts,m2v,m4v,mkv,moov,mov,mp4,mp3,mpeg,mpeg1,mpeg2,mpeg4,mpg,mpv,mt2s,mts,mxf,ogm,ogv,ps,qt,rm,rmvb,ts,vob,webm,wm,wmv,h264,rm</supportFormat>
    <supportWifiTransfter>1</supportWifiTransfter>
    <supportNotWifi>1</supportNotWifi>
    <Tips>
        <appVersion>1.7.0</appVersion>
        <info>
            <valid>0</valid>
            <frequency>60000</frequency>
            <link>https://itunes.apple.com/app/id577723645</link>
            <word>如果你觉得此应用不错，前去appstore评分？</word>
        </info>
    </Tips>
    
    <!--ptag:0 ffmpeg,1 system,2 web ，3 converter-->
    

    <Channel name="体育" type="1">
        
        <SubChannel iconURL="" name="快乐垂钓" type="1" >
            <streamURL>http://hlstest.imgo.tv/hvb4/index_512k.m3u8</streamURL>
            <streamURL ptag="3">http://live.api.hunantv.com/pc/getById?liveType=2&amp;liveId=218</streamURL>
            
         </SubChannel>
        <SubChannel iconURL="" name="先锋乒羽" type="1"   >
            <streamURL ptag="3">http://live.api.hunantv.com/pc/getById?liveType=2&amp;liveId=329</streamURL>
         </SubChannel>
        
    </Channel>
    
    <Channel name="资讯" type="2">
        
        <SubChannel iconURL="" name="茶频道" type="1" l="cctv1,cctv1">
            <streamURL ptag="3">http://live.api.hunantv.com/pc/getById?liveType=2&amp;liveId=578</streamURL>
            
        </SubChannel>
        <!--
        <SubChannel iconURL="" name="亚太卫视" type="1" l="cctv1,cctv1">
            <streamURL>http://v1.one-tv.com:1935/live/mpegts.stream/chunklist_w638788092.m3u8</streamURL>
            
        </SubChannel>
         -->
        <SubChannel iconURL="" name="家乐购" type="1" l="cctv1,cctv1">
            <streamURL>http://hqgwqgdq.vdnplus.com/channels/tvie/hqgwqgdq/m3u8:1000k</streamURL>
            
        </SubChannel>
        
        
    </Channel>
</Channels>